NPTFit/__init__.py
NPTFit/config_maps.py
NPTFit/create_mask.py
NPTFit/dnds_analysis.py
NPTFit/incgamma_fct.so
NPTFit/npll.so
NPTFit/nptf_scan.py
NPTFit/nptfit.py
NPTFit/pdf_sampler.py
NPTFit/pll.so
NPTFit/psf_compute.py
NPTFit/psf_correction.py
NPTFit/set_dirs.py
NPTFit/x_m.so
NPTFit-0.1.1.dist-info/DESCRIPTION.rst
NPTFit-0.1.1.dist-info/METADATA
NPTFit-0.1.1.dist-info/RECORD
NPTFit-0.1.1.dist-info/WHEEL
NPTFit-0.1.1.dist-info/metadata.json
NPTFit-0.1.1.dist-info/top_level.txt
