Metadata-Version: 2.0
Name: NPTFit
Version: 0.1.1
Summary: A Python package for Non-Poissonian Template Fitting
Home-page: https://github.com/bsafdi/NPTFit
Author: Siddharth Mishra-Sharma
Author-email: smsharma@princeton.edu
License: MIT
Platform: UNKNOWN
Requires-Dist: Cython
Requires-Dist: corner
Requires-Dist: healpy
Requires-Dist: jupyter
Requires-Dist: matplotlib
Requires-Dist: mpmath
Requires-Dist: numpy
Requires-Dist: pymultinest
